luxai_runner/__init__.py
luxai_runner/bot.py
luxai_runner/cli.py
luxai_runner/episode.py
luxai_runner/ext_to_command.py
luxai_runner/logger.py
luxai_runner/process.py
luxai_runner/utils.py
luxai_runner/tournament/__init__.py
luxai_runner/tournament/config.py
luxai_runner/tournament/matchmaking.py
luxai_runner/tournament/rankingsystem.py
luxai_runner/tournament/tournament.py
luxai_s2/__init__.py
luxai_s2/actions.py
luxai_s2/config.py
luxai_s2/env.py
luxai_s2/factory.py
luxai_s2/globals.py
luxai_s2/team.py
luxai_s2/unit.py
luxai_s2/version.py
luxai_s2/map/__init__.py
luxai_s2/map/bfs_deltas_gen.py
luxai_s2/map/board.py
luxai_s2/map/position.py
luxai_s2/map_generator/__init__.py
luxai_s2/map_generator/generator.py
luxai_s2/map_generator/symnoise.py
luxai_s2/map_generator/timing.py
luxai_s2/map_generator/visualize.py
luxai_s2/map_generator/visualize_samples.py
luxai_s2/pyvisual/__init__.py
luxai_s2/pyvisual/visualizer.py
luxai_s2/replay/__init__.py
luxai_s2/replay/replay.py
luxai_s2/spaces/__init__.py
luxai_s2/spaces/act_space.py
luxai_s2/spaces/obs_space.py
luxai_s2/state/__init__.py
luxai_s2/state/state.py
luxai_s2/state/stats.py
luxai_s2/state/typing.py
luxai_s2/tools/__init__.py
luxai_s2/tools/replay.py
luxai_s2/utils/__init__.py
luxai_s2/utils/animate.py
luxai_s2/utils/utils.py
luxai_s2/utils/heuristics/__init__.py
luxai_s2/utils/heuristics/bidding.py
luxai_s2/utils/heuristics/factory.py
luxai_s2/utils/heuristics/factory_placement.py
luxai_s2/wrappers/__init__.py
luxai_s2/wrappers/controllers.py
luxai_s2/wrappers/sb3.py
luxai_s2-3.0.1.dist-info/METADATA
luxai_s2-3.0.1.dist-info/WHEEL
luxai_s2-3.0.1.dist-info/entry_points.txt
luxai_s2-3.0.1.dist-info/top_level.txt
luxai_s2-3.0.1.dist-info/RECORD
